Metadata-Version: 2.1
Name: molodoymalchik
Version: 0.0.1
Summary: My Package
Author: Your Name
Author-email: petrkoldyshev@gmail.com
